rp2/__init__.py
rp2/abstract_accounting_method.py
rp2/abstract_country.py
rp2/abstract_entry.py
rp2/abstract_entry_set.py
rp2/abstract_report_generator.py
rp2/abstract_transaction.py
rp2/accounting_engine.py
rp2/balance.py
rp2/computed_data.py
rp2/configuration.py
rp2/configuration_schema.py
rp2/entry_types.py
rp2/gain_loss.py
rp2/gain_loss_set.py
rp2/in_transaction.py
rp2/input_data.py
rp2/intra_transaction.py
rp2/localization.py
rp2/logger.py
rp2/ods_parser.py
rp2/out_transaction.py
rp2/py.typed
rp2/rp2_configuration_translator.py
rp2/rp2_decimal.py
rp2/rp2_error.py
rp2/rp2_main.py
rp2/tax_engine.py
rp2/transaction_set.py
rp2/locales/en/LC_MESSAGES/messages.mo
rp2/locales/en_IE/LC_MESSAGES/messages.mo
rp2/locales/es/LC_MESSAGES/messages.mo
rp2/locales/ja/LC_MESSAGES/messages.mo
rp2/locales/kl/LC_MESSAGES/messages.mo
rp2/plugin/__init__.py
rp2/plugin/accounting_method/__init__.py
rp2/plugin/accounting_method/fifo.py
rp2/plugin/accounting_method/hifo.py
rp2/plugin/accounting_method/lifo.py
rp2/plugin/country/__init__.py
rp2/plugin/country/es.py
rp2/plugin/country/generic.py
rp2/plugin/country/ie.py
rp2/plugin/country/jp.py
rp2/plugin/country/us.py
rp2/plugin/report/__init__.py
rp2/plugin/report/abstract_ods_generator.py
rp2/plugin/report/open_positions.py
rp2/plugin/report/rp2_full_report.py
rp2/plugin/report/data/__init__.py
rp2/plugin/report/data/es/template_open_positions_es.ods
rp2/plugin/report/data/es/template_rp2_full_report_es.ods
rp2/plugin/report/data/generic/template_open_positions_en.ods
rp2/plugin/report/data/generic/template_rp2_full_report_en.ods
rp2/plugin/report/data/ie/template_open_positions_en_IE.ods
rp2/plugin/report/data/ie/template_rp2_full_report_en_IE.ods
rp2/plugin/report/data/ie/template_tax_report_ie_en_IE.ods
rp2/plugin/report/data/jp/template_open_positions_en.ods
rp2/plugin/report/data/jp/template_open_positions_kl.ods
rp2/plugin/report/data/jp/template_rp2_full_report_en.ods
rp2/plugin/report/data/jp/template_rp2_full_report_kl.ods
rp2-1.7.1.dist-info/LICENSE
rp2-1.7.1.dist-info/METADATA
rp2-1.7.1.dist-info/WHEEL
rp2-1.7.1.dist-info/entry_points.txt
rp2-1.7.1.dist-info/top_level.txt
rp2-1.7.1.dist-info/RECORD
