Metadata-Version: 2.1
Name: rp2
Version: 1.7.1
Summary: Privacy-focused, free, non-commercial, open-source, community-driven cryptocurrency tax calculator: it handles multiple coins/exchanges and computes long/short-term capital gains, cost bases, in/out lot relationships/fractioning, and account balances. It supports multiple countries and accounting menthods (FIFO, LIFO, HIFO), it features transparent computation for easy result verification, and it generates reports tax accountants can understand (e.g. form 8949).
Home-page: https://github.com/eprbell/rp2
Author: eprbell
License: Apache License 2.0
Project-URL: Source Code, https://github.com/eprbell/rp2
Project-URL: Developer Documentation, https://github.com/eprbell/rp2/blob/main/README.dev.md
Project-URL: User Documentation, https://github.com/eprbell/rp2/blob/main/README.md
Project-URL: Contact, https://eprbell.github.io/eprbell/about.html
Keywords: accounting,altcoin,bitcoin,BTC,capital gains,cost basis,crypto,cryptocurrency,DeFi,ETH,ethereum,finance,form 8949,NFT,privacy,wallet,tax
Classifier: Development Status :: 5 - Production/Stable
Classifier: Intended Audience :: End Users/Desktop
Classifier: License :: OSI Approved :: Apache Software License
Classifier: Operating System :: OS Independent
Classifier: Programming Language :: Python :: 3.8
Classifier: Programming Language :: Python :: 3.9
Classifier: Programming Language :: Python :: 3.10
Classifier: Programming Language :: Python :: 3.11
Classifier: Programming Language :: Python :: 3.12
Classifier: Topic :: Office/Business :: Financial :: Accounting
Classifier: Topic :: Utilities
Classifier: Typing :: Typed
License-File: LICENSE
Requires-Dist: Babel >=2.10.3
Requires-Dist: jsonschema >=3.2.0
Requires-Dist: prezzemolo >=0.0.4
Requires-Dist: python-dateutil >=2.8.2
Requires-Dist: pycountry >=24.6.1
Requires-Dist: pyexcel-ezodf >=0.3.4
Provides-Extra: dev
Requires-Dist: autopep8 ; extra == 'dev'
Requires-Dist: bandit ; extra == 'dev'
Requires-Dist: black ; extra == 'dev'
Requires-Dist: bumpversion ; extra == 'dev'
Requires-Dist: flake8 ; extra == 'dev'
Requires-Dist: isort ; extra == 'dev'
Requires-Dist: mypy ; extra == 'dev'
Requires-Dist: pep8 ; extra == 'dev'
Requires-Dist: pre-commit ; extra == 'dev'
Requires-Dist: pylint ; extra == 'dev'
Requires-Dist: pytest ; extra == 'dev'
Requires-Dist: pytest-mock ; extra == 'dev'
Requires-Dist: rope ; extra == 'dev'
Requires-Dist: types-jsonschema ; extra == 'dev'
Requires-Dist: types-python-dateutil ; extra == 'dev'
